setup.py
dictime/__init__.py
dictime/dictime.py
dictime/moment.py
dictime.egg-info/PKG-INFO
dictime.egg-info/SOURCES.txt
dictime.egg-info/dependency_links.txt
dictime.egg-info/not-zip-safe
dictime.egg-info/top_level.txt