Metadata-Version: 1.1
Name: dictime
Version: 0.0.2
Summary: Dictionary with the dimension of time
Home-page: https://github.com/stevepeak/dictime
Author: @stevepeak
Author-email: steve@stevepeak.net
License: Apache v2
Keywords: dict list expire future cache
Platform: UNKNOWN
Classifier: Development Status :: 4 - Beta
Classifier: License :: OSI Approved :: Apache Software License
